MANIFEST.in
README.rst
setup.py
django_kitsune.egg-info/PKG-INFO
django_kitsune.egg-info/SOURCES.txt
django_kitsune.egg-info/dependency_links.txt
django_kitsune.egg-info/not-zip-safe
django_kitsune.egg-info/requires.txt
django_kitsune.egg-info/top_level.txt
kitsune/__init__.py
kitsune/admin.py
kitsune/base.py
kitsune/html2text.py
kitsune/mail.py
kitsune/models.py
kitsune/monitor.py
kitsune/nagios.py
kitsune/renderers.py
kitsune/scripts.py
kitsune/utils.py
kitsune/views.py
kitsune/management/__init__.py
kitsune/management/commands/__init__.py
kitsune/management/commands/kitsune_cron.py
kitsune/management/commands/kitsune_cron_clean.py
kitsune/management/commands/kitsune_cronserver.py
kitsune/management/commands/kitsune_nagios_check.py
kitsune/management/commands/kitsune_run_job.py
kitsune/management/commands/kitsune_test_check.py
kitsune/migrations/0001_initial.py
kitsune/migrations/0002_auto__add_host.py
kitsune/migrations/0003_auto__del_field_job_host_name.py
kitsune/migrations/0004_auto__add_field_job_host.py
kitsune/migrations/0005_auto__add_field_job_last_result.py
kitsune/migrations/0006_auto__add_field_job_renderer.py
kitsune/migrations/0007_auto__add_field_job_log_clean_freq_unit__add_field_job_log_clean_freq_.py
kitsune/migrations/0008_auto__del_field_job_log_clean_freq_value__del_field_job_log_clean_freq.py
kitsune/migrations/0009_auto__add_notificationrule.py
kitsune/migrations/0010_auto__chg_field_notificationrule_frequency_value.py
kitsune/migrations/0011_auto__add_field_notificationrule_enabled.py
kitsune/migrations/0012_auto__del_field_notificationrule_frequency_unit__del_field_notificatio.py
kitsune/migrations/0013_auto__del_notificationrule__add_notificationgroup__add_notificationuse.py
kitsune/migrations/__init__.py
kitsune/templates/admin/kitsune/job/change_form.html
kitsune/templates/admin/kitsune/job/change_list.html
kitsune/templates/admin/kitsune/log/change_form.html
kitsune/templates/kitsune/error_message.txt
kitsune/templates/kitsune/mail_base.html
kitsune/templates/kitsune/mail_notification.html
kitsune/templates/kitsune/nagios_status_message.html
kitsune/templates/kitsune/status_code.html
kitsune/templatetags/__init__.py
kitsune/templatetags/kitsune_tags.py