Metadata-Version: 1.0
Name: django-kitsune
Version: 0.2.3
Summary: A Django Admin app to perform host server monitoring.
Home-page: https://github.com/tryolabs/django-kitsune
Author: Raul Garreta - Tryolabs
Author-email: raul@tryolabs.com
License: UNKNOWN
Platform: UNKNOWN
